pydp/__init__.py
pydp/_pydp.so
pydp/algorithms/__init__.py
pydp/algorithms/_algorithm.py
pydp/algorithms/numerical_mechanisms.py
pydp/algorithms/partition_selection.py
pydp/algorithms/quantile_tree.py
pydp/algorithms/laplacian/__init__.py
pydp/algorithms/laplacian/_bounded_algorithms.py
pydp/algorithms/laplacian/_count.py
pydp/algorithms/laplacian/_percentile.py
pydp/distributions/__init__.py
pydp/ml/__init__.py
pydp/ml/naive_bayes.py
pydp/ml/mechanisms/__init__.py
pydp/ml/mechanisms/base.py
pydp/ml/mechanisms/geometric.py
pydp/ml/mechanisms/laplace.py
pydp/ml/util/__init__.py
pydp/ml/util/accountant.py
pydp/ml/util/utils.py
pydp/ml/util/validation.py
pydp/util/__init__.py
python/__init__.py
python_dp-1.1.4.dist-info/LICENSE
python_dp-1.1.4.dist-info/METADATA
python_dp-1.1.4.dist-info/WHEEL
python_dp-1.1.4.dist-info/top_level.txt
python_dp-1.1.4.dist-info/RECORD
