Metadata-Version: 2.1
Name: python-dp
Version: 1.1.4
Summary: Python API for Google's Differential Privacy library
Home-page: https://github.com/OpenMined/PyDP
Author: Chinmay Shah
Author-email: chinmayshah3899@gmail.com
License: Apache-2.0
Keywords: pydp
Classifier: Development Status :: 5 - Production/Stable
Classifier: Intended Audience :: Developers
Classifier: Natural Language :: English
Classifier: Programming Language :: Python :: 3
Classifier: Programming Language :: Python :: 3.8
Classifier: Programming Language :: Python :: 3.9
Classifier: Programming Language :: Python :: 3.10
Classifier: Programming Language :: Python :: 3.11
Requires-Python: >=3.8
License-File: LICENSE
